{

    "le_deplacement" : {
        "name" : "le_deplacement",
        "realname": "Gares",
        "description" : "Gares et aérodromes proches de chez vous !",
        "group" : "Transports",
        "type" : "distance_based",
        "params" : {
            "min_dist" : 0,
            "max_dist" : 1000,
            "dist_scale" : "linear"
        }
    },
            
    "velov" : {
        "name" : "velov",
        "realname":"Velo'v",
        "description" : "Station de vélos en libre service à proximité !",
        "type" : "dist_dens_based",
        "group" : "Transports",
        "params" : {
            "min_dist" : 0,
            "max_dist" : 500,
            "min_density" : 3,
            "max_density" : 100000,
            "dist_coeff" : 2,
            "dens_coeff": 1,
            "radius" : 500,
            "dist_scale" : "linear",
            "dens_scale" : "linear"
        }
    },
            
    "tcl" : {
        "name" : "tcl",
        "realname":"TCL",
        "description" : "Stations de métro, tramway et arrêts de bus",
        "group" : "Transports",
        "type" : "dist_dens_based",
        "params" : {
            "min_dist" : 0,
            "max_dist" : 500,
            "min_density" : 3,
            "max_density" : 10000,
            "dist_coeff" : 2,
            "dens_coeff": 1,
            "radius" : 500,
            "dist_scale" : "linear",
            "dens_scale" : "linear"
        }
    },
    

    "bruit" : {
        "name" : "bruit",
        "realname": "Bruit",
        "description": "Niveau de bruit ambiant moyen dans votre zone",
        "group" : "Vie quotidienne",
        "type" : "custom",
        "params" : {
            "radius" : 500
        }
    },
            
    "le_enseignement" : {
        "name" : "le_enseignement",
        "realname" : "Enseignement",
        "description" : "Ensemble des écoles, collèges, lycées et universités",
        "group" : "Vie quotidienne",
        "type" : "dist_dens_based",
        "params" : {
            "min_dist" : 0,
            "max_dist" : 1000,
            "min_density" : 3,
            "max_density" : 10000,
            "dist_coeff" : 3,
            "dens_coeff": 2,
            "radius" : 1000,
            "dist_scale" : "linear",
            "dens_scale" : "linear"
        }
    },
            
    "le_culte" : {
        "name" : "le_culte",
        "realname": "Culte",
        "group" : "Vie quotidienne",
        "description" : "Lieux de cultes principaux : églises, mosquées, synagogues, temples ...",
        "type" : "distance_based",
        "params" : {
            "min_dist" : 0,
            "max_dist" : 2000,
            "dist_scale" : "linear"
        }
    },
            
    "pit_commerce_et_service": {
        "name" : "pit_commerce_et_service",
        "realname": "Commerces et services",
        "description" : "Magasins, boutiques, associations ...",
        "group" : "Vie quotidienne",
        "type" : "dist_dens_based",
        "params" : {
            "min_dist" : 0,
            "max_dist" : 1000,
            "min_density" : 10,
            "max_density" : 100000,
            "dist_coeff" : 1,
            "dens_coeff": 3,
            "radius" : 1000,
            "dist_scale" : "linear",
            "dens_scale" : "linear"
        }
    },
    
    "le_administration":{
        "name" : "le_administration",
        "realname": "Mairies",
        "description" : "Mairies",
        "group" : "Administration et santé",
        "type" : "distance_based",
        "params" : {
            "min_dist" : 0,
            "max_dist" : 1000,
            "dist_scale" : "linear"
        }
    },
                
    "le_urgence" : {
        "name" : "le_urgence",
        "realname":"Sécurité",
        "description" : "Urgences : polices, gendarmeries, pompiers",
        "group" : "Administration et santé",
        "type" : "distance_based",
        "params" : {
            "min_dist" : 0,
            "max_dist" : 1000,
            "dist_scale" : "linear"
        }
    },
            
    "le_sante" : {
        "name" : "le_sante",
        "realname": "Santé",
        "description" : "Cliniques et hôpitaux",
        "group" : "Administration et santé",
        "type" : "distance_based",
        "params" : {
            "min_dist" : 0,
            "max_dist" : 5000,
            "dist_scale" : "linear"
        }
    },
    
    "pit_hotellerie":{
        "name" : "pit_hotellerie",
        "realname": "Hôtellerie",
        "description" : "",
        "group" : "Hôtellerie et restauration",
        "type" : "density_based",
        "params" : {
            "min_density" : 5,
            "max_density" : 10000,
            "radius":500,
            "dens_scale" : "linear"
        }
    },
        
    "pit_hotellerie_plein_air" : {
        "name" : "pit_hotellerie_plein_air",
        "realname": "Campings",
        "group" : "Hôtellerie et restauration",
        "description" : "",
        "type" : "density_based",
        "params" : {
            "min_density" : 5,
            "max_density" : 100000,
            "radius" : 1000,
            "dens_scale" : "linear"
        }
    },
            
    "pit_restauration": {
        "name" : "pit_restauration",
        "realname": "Restauration",
        "description" : "",
        "group" : "Hôtellerie et restauration",
        "type" : "density_based",
        "params" : {
            "min_density" : 10,
            "max_density" : 10000,
                    "radius":500,
                    "dens_scale": "linear"
        }
    },
            
    "pit_degustation":{
        "name" : "pit_degustation",
        "realname": "Dégustation",
        "description" : "Dégustation de vins et de spécialités locales !",
        "group" : "Hôtellerie et restauration",
        "type" : "dist_dens_based",
        "params" : {
            "min_dist" : 0,
            "max_dist" : 2000,
            "min_density" : 3,
            "max_density" : 10000,
            "dist_coeff" : 3,
            "dens_coeff": 1,
            "radius" : 2000,
            "dist_scale" : "linear",
            "dens_scale" : "linear"
        }
    },
    
    "pit_patrimoine_culturel": {
        "name" : "pit_patrimoine_culturel",
        "realname": "Patrimoine culturel",
        "description" : "Ensemble de lieux et monuments historiques",
        "group" : "Patrimoine culturel et naturel",
        "type" : "density_based",
        "params" : {
            "min_density" : 5,
            "max_density" : 10000,
            "dens_scale" : "linear",
            "radius":500
        }
    },
    
    "pit_patrimoine_naturel" : {
        "name" : "pit_patrimoine_naturel",
        "realname": "Patrimoine naturel",
        "description" : "Lacs, îles, plan d'eau",
        "group" : "Patrimoine culturel et naturel",
        "type" : "distance_based",
        "params" : {
            "min_dist" : 0,
            "max_dist" : 2000,
            "dist_scale" : "linear"
        }
    },
    
 
    "pit_hebergement_locatif":{
        "name" : "pit_hebergement_locatif",
        "realname":"Hébergement locatif",
        "group" : "Hébergement",
        "type" : "density_based",
        "params" : {
            "min_density" : 10,
            "max_density" : 10000,
            "dens_scale" : "linear",
            "radius":500
        }
    },

    "pit_hebergement_collectif":{
        "name" : "pit_hebergement_collectif",
        "realname":"Hébergement collectif",
        "group" : "Hébergement",
        "type" : "density_based",
        "params" : {
            "min_density" : 10,
            "max_density" : 10000,
            "radius":500,
            "dens_scale" : "linear"
        }
    },
    
    "pit_equipement" : {
        "name" : "pit_equipement",
        "realname":"Loisirs",
        "type" : "dist_dens_based",
        "group" : "Sport et loisirs",
        "params" : {
            "min_dist" : 0,
            "max_dist" : 2000,
            "min_density" : 5,
            "max_density" : 100000,
            "dist_coeff" : 1,
            "dens_coeff": 3,
            "radius" : 2000,
            "dist_scale" : "linear",
            "dens_scale" : "linear"
        }
    },

    "le_sport" : {
        "name" : "le_sport",
        "realname":"Sport",
        "type" : "dist_dens_based",
        "group" : "Sport et loisirs",
        "params" : {
            "min_dist" : 0,
            "max_dist" : 2000,
            "min_density" : 3,
            "max_density" : 100000,
            "dist_coeff" : 1,
            "dens_coeff": 3,
            "radius" : 2000,
            "dist_scale" : "linear",
            "dens_scale" : "linear"
        }
    }
}