{"criteres":[{"name": "Bruit", "code": "bruit_psd"}, {"name": "Administration", "code": "le_administration_psd"}, {"name": "Lieux de culte", "code": "le_culte_psd"}, {"name": "Déplacements", "code": "le_deplacement_psd"}, {"name": "Enseignement", "code": "le_enseignement_psd"}, {"name": "Habitat", "code": "le_habitat_psd"}, {"name": "Intercommunalité", "code": "le_intercommunalite_psd"}, {"name": "Santé", "code": "le_sante_psd"}, {"name": "Sport", "code": "le_sport_psd"}, {"name": "Urgences", "code": "le_urgence_psd"}, {"name": "Commerces et services", "code": "pit_commerce_et_service_psd"}, {"name": "Dégustations", "code": "pit_degustation_psd"}, {"name": "Equipements", "code": "pit_equipement_psd"}, {"name": "Hébergement collectif", "code": "pit_hebergement_collectif_psd"}, {"name": "Hébergement locatif", "code": "pit_hebergement_locatif_psd"}, {"name": "Hôtellerie plein air", "code": "pit_hotellerie_plein_air_psd"}, {"name": "Hôtels", "code": "pit_hotellerie_psd"}, {"name": "Patrimoine culturel", "code": "pit_patrimoine_culturel_psd"}, {"name": "Patrimoine naturel", "code": "pit_patrimoine_naturel_psd"}, {"name": "Restauration", "code": "pit_restauration_psd"}, {"name": "Transports en commun TCL", "code": "tcl_psd"}, {"name": "Vélo'v", "code": "velov_psd"}]}
